Metadata-Version: 2.4
Name: eqbool
Version: 0.3
Summary: Testing boolean expressions for equivalence
Home-page: https://github.com/kosarev/eqbool/
Author: Ivan Kosarev
Author-email: Ivan Kosarev <mail@ivankosarev.com>
License-Expression: MIT
Project-URL: Homepage, https://github.com/kosarev/eqbool
Project-URL: Bug Tracker, https://github.com/kosarev/eqbool/issues
Classifier: Development Status :: 4 - Beta
Classifier: Intended Audience :: Developers
Classifier: Intended Audience :: Information Technology
Classifier: Intended Audience :: Education
Classifier: Operating System :: OS Independent
Classifier: Programming Language :: C++
Classifier: Programming Language :: Python :: 3
Classifier: Programming Language :: Python :: Implementation :: CPython
Classifier: Topic :: Software Development
Classifier: Topic :: Software Development :: Libraries
Requires-Python: >=3.7
License-File: LICENSE
Dynamic: author
Dynamic: home-page
Dynamic: license-file
